disk_bench-0.2.1.dist-info/DESCRIPTION.rst
disk_bench-0.2.1.dist-info/METADATA
disk_bench-0.2.1.dist-info/RECORD
disk_bench-0.2.1.dist-info/WHEEL
disk_bench-0.2.1.dist-info/entry_points.txt
disk_bench-0.2.1.dist-info/metadata.json
disk_bench-0.2.1.dist-info/top_level.txt
diskbench/cli.py
diskbench/fio.py
diskbench/testing.py
diskbench/version.py
diskbench/tests/test_cli.py
diskbench/tests/test_fio.py
diskbench/tests/data/fio-output.json
diskbench/tests/data/table-output.txt
