Metadata-Version: 2.0
Name: disk-bench
Version: 0.2.1
Summary: CLI tool to benchmark drive performance
Home-page: https://github.com/rsyring/disk-bench
Author: Randy Syring
Author-email: randy@thesyrings.us
License: MIT
Platform: UNKNOWN
Classifier: Development Status :: 4 - Beta
Classifier: License :: OSI Approved :: MIT License
Classifier: Programming Language :: Python :: 3
Classifier: Programming Language :: Python :: 3.5
Classifier: Programming Language :: Python :: 3.6
Classifier: Programming Language :: Python :: 3.7
Requires-Dist: click
Requires-Dist: sh
Requires-Dist: tableprint
